Workbook

Sheet 前提
A1: 前提（Assumptions）― 黄=編集可能入力 / 緑=数式算出。Solafune（衛星データ解析×経済安保デュアルユース）
A3: 項目 | B3: 値 | C3: 単位 | D3: 仮 | E3: 注記/出典
A4: ■ ファンド前提（最新・確定）
A5: ファンド総額（3号） | B5: 150 | C5: 億円 | E5: 1号30億 DPI2.0X / 2号80億 DPI1.5X
A6: 管理報酬率 | B6: 0.02 | C6: /年 | E6: 費用2%（10年累計の目安として控除）
A7: キャリー | B7: 0.2 | E7: 成功報酬20%
A8: 運用年数 | B8: 10 | C8: 年 | E8: 投資5＋回収5（最大+2）
A9: 費用控除後 投資可能資本 | B9: =B5*(1-B6*8.3) | C9: 億円 | D9: 仮 | E9: ≒約125億円（管理2%×8.3年相当の費用累計を控除した投資可能枠の近似）
A10: ファンドリターナー閾値 | B10: 150 | C10: 億円 | E10: 対象1社ポジション回収額がこれ以上でTRUE
A11: 目標ネットDPI | B11: 3 | C11: X | E11: グロス約4.3X（対投資可能資本）
A12: 初回チケット | B12: 5.5 | C12: 億円 | E12: 初回投資額
A13: 集中度上限（対ファンド総額） | B13: 0.13 | E13: 集中度上限13%（対ファンド総額150億）
A14: 集中度上限 金額 | B14: =B5*B13 | C14: 億円 | E14: ≒約20億円（=ファンド総額150億×13%）
A15: リザーブ比率：初回（ファンド全体・集計） | B15: 0.45 | E15: 初回:追加=45:55
A16: リザーブ比率：追加（ファンド全体・集計） | B16: 0.55 | E16: 初回:追加=45:55
A17: 目標エントリー持分（テーゼ） | B17: 0.15 | E17: 目標15%。実エントリー持分は数式算出し差を注記
A18: Solafune総コミット（初回+追加, super pro-rata） | B18: =B12+11 | C18: 億円 | D18: 仮
A19: ■ 投資・バリュエーション前提（仮・要検証）
A20: 投資時点 Pre-Val（投資前評価） | B20: 31 | C20: 億円 | D20: 仮 | E20: シード〜プレA拡大組成で交渉する投資前評価（非開示につき置き）。Post=Pre31+初回5.5=36.5
A21: 初回投資額（=初回チケット） | B21: =B12 | C21: 億円 | E21: 前提!B12を参照
A22: EV/Sales 倍率（Exit評価） | B22: 17 | C22: 倍 | D22: 仮 | E22: comps採用群中央値10倍を起点にソフト比率・粗利・主権プレミアムで上位寄せ→17倍。Palantir現況60.7倍はバブル除外。感度12〜20
A23: Exit持分（希薄化後） | B23: 0.12 | D23: 仮 | E23: 10〜12%。希薄化後の想定
A24: Exit年 | B24: 2032 | C24: 年 | D24: 仮 | E24: 2032年Exit想定
A25: 売上CAGR（2031以降延伸） | B25: 0.09 | D25: 仮 | E25: 2030売上85億を延伸→2032≒100億（Exit評価1,500-1,800億に整合）。高成長想定なら引上げ
A26: セカンダリ割引率 | B26: 0.3 | D26: 仮 | E26: セカンダリExit時の割引
A28: ■ 売上前提（億円, 編集可能。PLが参照）
A29: 年度 | B29: 2026 | C29: 2027 | D29: 2028 | E29: 2029 | F29: 2030
A30: 売上（仮） | B30: 4 | C30: 10 | D30: 22 | E30: 45 | F30: 85 | H30: ← 2026-2030は入力。2031/2032はPLでCAGR延伸
A31: GM%（仮, 逓増） | B31: 0.6 | C31: 0.63 | D31: 0.66 | E31: 0.69 | F31: 0.72 | H31: ← 60%→72% 年次逓増（入力）

Sheet PL
A1: PL（損益, 億円）2026〜2032 ― 売上は前提参照、2031/2032はCAGR延伸（数式）
A3: 項目（億円） | B3: 2026 | C3: 2027 | D3: 2028 | E3: 2029 | F3: 2030 | G3: 2031 | H3: 2032
A4: 売上高 | B4: =&#21069;&#25552;!$B$30 | C4: =&#21069;&#25552;!$C$30 | D4: =&#21069;&#25552;!$D$30 | E4: =&#21069;&#25552;!$E$30 | F4: =&#21069;&#25552;!$F$30 | G4: =F4*(1+&#21069;&#25552;!$B$25) | H4: =G4*(1+&#21069;&#25552;!$B$25)
A5: 前年比成長率 | B5: ― | C5: =C4/B4-1 | D5: =D4/C4-1 | E5: =E4/D4-1 | F5: =F4/E4-1 | G5: =G4/F4-1 | H5: =H4/G4-1
A6: 粗利率 GM% | B6: =&#21069;&#25552;!$B$31 | C6: =&#21069;&#25552;!$C$31 | D6: =&#21069;&#25552;!$D$31 | E6: =&#21069;&#25552;!$E$31 | F6: =&#21069;&#25552;!$F$31 | G6: =&#21069;&#25552;!$F$31 | H6: =&#21069;&#25552;!$F$31
A7: 粗利 | B7: =B4*B6 | C7: =C4*C6 | D7: =D4*D6 | E7: =E4*E6 | F7: =F4*F6 | G7: =G4*G6 | H7: =H4*H6
A8: 営業費用(簡易=売上×40%) | B8: =B4*0.40 | C8: =C4*0.40 | D8: =D4*0.40 | E8: =E4*0.40 | F8: =F4*0.40 | G8: =G4*0.40 | H8: =H4*0.40
A9: 営業損益 | B9: =B7-B8 | C9: =C7-C8 | D9: =D7-D8 | E9: =E7-E8 | F9: =F7-F8 | G9: =G7-G8 | H9: =H7-H8
A11: 注：2031/2032売上＝前年×(1+前提CAGR)。GM%は2030水準を維持（保守）。OPEXは簡易係数。

Sheet Exit
A1: Exit（企業価値 = Exit売上 × EV/Sales）― IPO/M&A=企業価値、セカンダリ=×(1−割引率)
A3: 項目 | B3: 値 | C3: 単位 | D3: 参照/数式の意味
A4: Exit年 | B4: =&#21069;&#25552;!$B$24 | C4: 年 | D4: 前提!Exit年
A5: Exit時 売上 | B5: =PL!H4 | C5: 億円 | D5: PL!2032売上（CAGR延伸）
A6: EV/Sales 倍率 | B6: =&#21069;&#25552;!$B$22 | C6: 倍 | D6: 前提!EV/Sales
A7: Exit企業価値（基準） | B7: =B5*B6 | C7: 億円 | D7: Exit売上×EV/Sales
A9: ■ Exit経路別 企業価値
A10: ① IPO（東証グロース） | B10: =B7 | C10: 億円 | D10: 企業価値そのまま
A11: ② M&A（重工/商社プライム） | B11: =B7 | C11: 億円 | D11: 企業価値そのまま
A12: ③ セカンダリ | B12: =B7*(1-&#21069;&#25552;!$B$26) | C12: 億円 | D12: 企業価値×(1−割引率)

Sheet リターン
A1: リターン ― エントリー持分/希薄化/Exit持分/MOIC/ポジション/ファンド倍率/ファンドリターナー判定
A3: 項目 | B3: 値 | C3: 単位 | D3: 数式の意味
A4: 初回投資額 | B4: =&#21069;&#25552;!$B$21 | C4: 億円 | D4: 前提!初回投資
A5: 投資時点 Pre-Val（投資前） | B5: =&#21069;&#25552;!$B$20 | C5: 億円 | D5: 前提!Post-Val
A6: エントリー持分（数式） | B6: =&#21069;&#25552;!$B$21/(&#21069;&#25552;!$B$20+&#21069;&#25552;!$B$21) | D6: 初回投資/(Post-Val+初回投資)
A7: 目標エントリー持分（テーゼ） | B7: =&#21069;&#25552;!$B$17 | D7: 前提!目標15%
A8: エントリー持分 vs 目標 差 | B8: =B6-B7 | D8: 実−目標（注記用）
A9: Exit持分（希薄化後） | B9: =&#21069;&#25552;!$B$23 | D9: 前提!Exit持分
A10: 希薄化（エントリー→Exit） | B10: =B6-B9 | D10: エントリー持分−Exit持分
A11: Exit企業価値（基準） | B11: =Exit!$B$7 | C11: 億円 | D11: Exit!基準企業価値
A12: ポジション回収額 | B12: =Exit!$B$7*&#21069;&#25552;!$B$23 | C12: 億円 | D12: Exit企業価値×Exit持分
A13: MOIC（対初回チケット5.5億・参考） | B13: =B12/B4 | C13: X | D13: ポジション/初回投資
A14: ファンド倍率（対総額） | B14: =B12/&#21069;&#25552;!$B$5 | C14: X | D14: ポジション/ファンド総額
A15: ファンドリターナー閾値 | B15: =&#21069;&#25552;!$B$10 | C15: 億円 | D15: 前提!閾値150億
A16: ファンドリターナー判定 | B16: =IF(B12>=&#21069;&#25552;!$B$10,"&#9675; &#12501;&#12449;&#12531;&#12489;&#12522;&#12479;&#12540;&#12490;&#12540;&#25104;&#31435;","&#215; &#19981;&#25104;&#31435;") | C16: 判定 | D16: IF(ポジション>=閾値150,○,×)
A17: MOIC（対総コミット16.5億） | B17: =B12/&#21069;&#25552;!$B$18 | C17: X
A18: ■ 必要Exit企業価値（閾値150億 到達に必要）
A19: 持分10%で必要なExit企業価値 | B19: =&#21069;&#25552;!$B$10/0.10 | C19: 億円 | D19: 150/10%
A20: 持分11%で必要なExit企業価値 | B20: =&#21069;&#25552;!$B$10/0.11 | C20: 億円 | D20: 150/11%≒1,360億
A21: 現Exit持分で必要なExit企業価値 | B21: =&#21069;&#25552;!$B$10/&#21069;&#25552;!$B$23 | C21: 億円 | D21: 150/Exit持分
A22: 投資後Post-Val（=Pre+初回投資） | B22: =&#21069;&#25552;!$B$20+&#21069;&#25552;!$B$21 | C22: 億円
A23: 注：エントリー持分=初回投資/(Pre-Val+初回投資)=初回投資/投資後Post-Val。基本=Pre31億+初回5.5億→投資後Post36.5億→5.5/36.5≒15.1%（単独リードでPreを30〜35億に交渉／教材「持分=チケット/Post」と整合）。下方=Pre40億据置なら5.5/45.5≒12.1%でも検算成立。Exit持分=希薄化後（前提B23=12%）。MOICは対初回37.5X(参考)と対総コミット12.5Xを併記。

Sheet 感度分析
A1: 感度分析 ― ポジション回収額(億円) = Exit売上 × EV/Sales × Exit持分。緑=150億超(ファンドリターナー成立域)
A3: ポジション回収額(億円)
A4: EV/Sales ＼ Exit持分 | B4: 0.08 | C4: 0.1 | D4: 0.11 | E4: 0.12
A5: 12 | B5: =Exit!$B$5*$A5*B$4 | C5: =Exit!$B$5*$A5*C$4 | D5: =Exit!$B$5*$A5*D$4 | E5: =Exit!$B$5*$A5*E$4
A6: 15 | B6: =Exit!$B$5*$A6*B$4 | C6: =Exit!$B$5*$A6*C$4 | D6: =Exit!$B$5*$A6*D$4 | E6: =Exit!$B$5*$A6*E$4
A7: 17 | B7: =Exit!$B$5*$A7*B$4 | C7: =Exit!$B$5*$A7*C$4 | D7: =Exit!$B$5*$A7*D$4 | E7: =Exit!$B$5*$A7*E$4
A8: 18 | B8: =Exit!$B$5*$A8*B$4 | C8: =Exit!$B$5*$A8*C$4 | D8: =Exit!$B$5*$A8*D$4 | E8: =Exit!$B$5*$A8*E$4
A9: 20 | B9: =Exit!$B$5*$A9*B$4 | C9: =Exit!$B$5*$A9*C$4 | D9: =Exit!$B$5*$A9*D$4 | E9: =Exit!$B$5*$A9*E$4
A12: 参考：Exit企業価値(億円) = Exit売上 × EV/Sales
A13: EV/Sales | B13: Exit企業価値 | C13: 判定@現Exit持分
A14: =$A5 | B14: =Exit!$B$5*$A14 | C14: =IF(Exit!$B$5*$A14*&#21069;&#25552;!$B$23>=&#21069;&#25552;!$B$10,"&#9675;","&#215;")
A15: =$A6 | B15: =Exit!$B$5*$A15 | C15: =IF(Exit!$B$5*$A15*&#21069;&#25552;!$B$23>=&#21069;&#25552;!$B$10,"&#9675;","&#215;")
A16: =$A7 | B16: =Exit!$B$5*$A16 | C16: =IF(Exit!$B$5*$A16*&#21069;&#25552;!$B$23>=&#21069;&#25552;!$B$10,"&#9675;","&#215;")
A17: =$A8 | B17: =Exit!$B$5*$A17 | C17: =IF(Exit!$B$5*$A17*&#21069;&#25552;!$B$23>=&#21069;&#25552;!$B$10,"&#9675;","&#215;")
A18: =$A9 | B18: =Exit!$B$5*$A18 | C18: =IF(Exit!$B$5*$A18*&#21069;&#25552;!$B$23>=&#21069;&#25552;!$B$10,"&#9675;","&#215;")
A20: 読み方：各セル=ポジション回収額(=Exit売上×EV/Sales×Exit持分)。150億以上=緑=ファンドリターナー成立。Exit売上はExit!B5(=PL2032)に連動。EV/SalesはA列(黄)を変更すると表1・表2・判定が再計算。

Sheet ポートフォリオ
A1: ポートフォリオ構築（べき乗則）― net DPI 3.0X はアウトライヤーの積み上げで作る
A2: ※ Solafune以外の9社は「分布の形」を示す例示（仮・要検証）。ただし勝ち馬B＝Humanity Brain（防衛装備庁採択の認知戦AI）は実在候補。黄=入力／回収F=想定comp倍率(J)×想定Exit売上(K)×想定Exit持分(L)の逆算式、MOIC E=F/D。H列=候補領域・I列=倍率根拠（領域→comp→MOICの橋）。Solafune行はリターン!B12連動（全チェーン駆動）、投下は前提!B18連動。
A4: # | B4: 会社 | C4: 区分 | D4: 投下資本(億) | E4: MOIC(X) | F4: 回収額(億) | G4: 回収シェア | H4: 想定候補領域（仮） | I4: 倍率根拠（TAM/Exit comp） | J4: 想定comp倍率(仮) | K4: 想定Exit売上(億,仮) | L4: 想定Exit持分%(仮)
A5: 1 | B5: Solafune | C5: ★ファンドリターナー | D5: =&#21069;&#25552;!$B$18 | E5: =F5/D5 | F5: =&#12522;&#12479;&#12540;&#12531;!$B$12 | G5: =F5/$F$15 | H5: 衛星×AI解析レイヤー（本命） | I5: EV/Sales17倍×Exit売上101億（§5統計導出）＝206億 | J5: ←リターン連動
A6: 2 | B6: Humanity Brain | C6: ホームラン(7-8X+)｜実在候補 | D6: 16 | E6: =F6/D6 | F6: =J6*K6*L6 | G6: =F6/$F$15 | H6: 認知戦対策AI／世論分布の予測（防衛装備庁「社会シミュレーション」採択） | I6: 認知ドメインの解析レイヤー＝Solafune(物理GEOINT)の隣接。防衛装備庁採択＝政府アンカー、デュアルユース・ソフト層で天井高。comp17倍×想定Exit売上80億×想定持分10%→EV1,360億・回収136億（8.5X級）。comps/Exit薄く要検証、influence-opsのESG論点も［仮・要検証］ | J6: 17 | K6: 80 | L6: 0.1
A7: 3 | B7: C | C7: 3-5X級 | D7: 14 | E7: =F7/D7 | F7: =J7*K7*L7 | G7: =F7/$F$15 | H7: 都市鉱山・精錬/リサイクル技術 | I7: 都市鉱山・精錬/リサイクル：CRMA(重要原材料法)追い風・循環経済TAM拡大。comp10倍×想定Exit売上70億×想定持分10%→EV700億・回収70億（5X級）［仮・要検証］ | J7: 10 | K7: 70 | L7: 0.1
A8: 4 | B8: D | C8: 3-5X級 | D8: 13 | E8: =F8/D8 | F8: =J8*K8*L8 | G8: =F8/$F$15 | H8: 海上物流・港湾ISR監視 | I8: 海上物流・港湾ISR監視：防衛ISR予算・経済安保。ハード薄めSaaS。comp8倍×想定Exit売上65億×想定持分9%→EV520億・回収45.5億（3.5X級）［仮・要検証］ | J8: 8 | K8: 65 | L8: 0.0875
A9: 5 | B9: E | C9: 1-2X級 | D9: 13 | E9: =F9/D9 | F9: =J9*K9*L9 | G9: =F9/$F$15 | H9: 資源インフラ向けセンシング基盤 | I9: 資源インフラ向けセンシング基盤：黎明期・単価不確実。comp7倍×想定Exit売上57億×想定持分8%→EV399億・回収29.9億（2.3X級）［仮・要検証］ | J9: 7 | K9: 57 | L9: 0.074937343
A10: 6 | B10: F | C10: 1-2X級 | D10: 12 | E10: =F10/D10 | F10: =J10*K10*L10 | G10: =F10/$F$15 | H10: 同領域 早期SU | I10: 同領域 早期SU：分布の中位。comp6倍×想定Exit売上45億×想定持分7%→EV270億・回収18億（1.5X級）［仮・要検証］ | J10: 6 | K10: 45 | L10: 0.066666667
A11: 7 | B11: G | C11: 1-2X級(元本回収) | D11: 11 | E11: =F11/D11 | F11: =J11*K11*L11 | G11: =F11/$F$15 | H11: 同領域 早期SU | I11: 同領域 早期SU（元本回収）：comp5倍×想定Exit売上40億×想定持分6%→EV200億・回収11億（1.0X）［仮・要検証］ | J11: 5 | K11: 40 | L11: 0.055
A12: 8 | B12: H | C12: 0-1X(部分毀損) | D12: 10 | E12: =F12/D12 | F12: =J12*K12*L12 | G12: =F12/$F$15 | H12: 同領域 早期SU | I12: 同領域 早期SU（部分毀損）：comp5倍×想定Exit売上25億×想定持分5%→EV125億・回収5億（0.5X）［仮・要検証］ | J12: 5 | K12: 25 | L12: 0.04
A13: 9 | B13: I | C13: 0-1X | D13: 9 | E13: =F13/D13 | F13: =J13*K13*L13 | G13: =F13/$F$15 | H13: 同領域 早期SU | I13: 同領域 早期SU（0-1X）：comp4倍×想定Exit売上18億×想定持分5%→EV72億・回収2.7億（0.3X）［仮・要検証］ | J13: 4 | K13: 18 | L13: 0.0375
A14: 10 | B14: J | C14: 全損 | D14: 8 | E14: =F14/D14 | F14: =J14*K14*L14 | G14: =F14/$F$15 | H14: 同領域 早期SU | I14: 同領域 早期SU（全損）：想定Exit持分0%（希薄化/毀損で消滅）→回収0億。分布の裾で期待値を作る［仮・要検証］ | J14: 4 | K14: 12 | L14: 0
B15: 合計（10社） | C15: グロス倍率→ | D15: =SUM(D5:D14) | E15: =F15/D15 | F15: =SUM(F5:F14) | G15: 1
B17: ■ 検算（グロス→ネット）
B18: 投下資本合計(億) | D18: =D15
B19: グロス回収合計(億) | D19: =F15
B20: グロス倍率（対投下資本） | D20: =F15/D15
B21: ファンド総額(億) | D21: =&#21069;&#25552;!$B$5
B22: LP分配=元本+利益80% | D22: =&#21069;&#25552;!$B$5+0.8*(F15-&#21069;&#25552;!$B$5)
B23: GPキャリー20% | D23: =0.2*(F15-&#21069;&#25552;!$B$5)
B24: ★ ネットDPI（対ファンド総額） | D24: =(&#21069;&#25552;!$B$5+0.8*(F15-&#21069;&#25552;!$B$5))/&#21069;&#25552;!$B$5
B25: 参考：Solafune単独のファンド倍率 | D25: =&#12522;&#12479;&#12540;&#12531;!$B$14
B26: 参考：上位2社の回収シェア | D26: =(F5+F6)/F15
B28: ■ リザーブ検算（社別投下の集計→ファンド全体比）
B29: 初回合計（=初回チケット5.5×10社） | D29: =&#21069;&#25552;!$B$12*10
B30: 追加合計（=投下合計−初回合計） | D30: =D15-&#21069;&#25552;!$B$12*10
B31: → 初回:追加 比率（≒45:55に一致） | D31: =(&#21069;&#25552;!$B$12*10)/D15
